garmin_uploader/__init__.py
garmin_uploader/api.py
garmin_uploader/cli.py
garmin_uploader/help.txt
garmin_uploader/user.py
garmin_uploader/workflow.py
garmin_uploader-1.0.10.dist-info/LICENSE.txt
garmin_uploader-1.0.10.dist-info/METADATA
garmin_uploader-1.0.10.dist-info/WHEEL
garmin_uploader-1.0.10.dist-info/entry_points.txt
garmin_uploader-1.0.10.dist-info/top_level.txt
garmin_uploader-1.0.10.dist-info/RECORD
