Metadata-Version: 2.1
Name: garmin-uploader
Version: 1.0.10
Summary: A tool to upload FIT, GPX, and TCX filesto the Garmin Connect web site.
Home-page: https://github.com/La0/garmin-uploader
Author: Bastien Abadie
Author-email: bastien@nextcairn.com
License: GPL
Keywords: GARMIN CONNECT GPS TCX GPX FIT UPLOAD UPLOADER
Platform: UNKNOWN
Classifier: Development Status :: 4 - Beta
Classifier: Environment :: Console
Classifier: Intended Audience :: End Users/Desktop
Classifier: License :: OSI Approved :: GNU General Public License (GPL)
Classifier: Programming Language :: Python
Classifier: Programming Language :: Python :: 2
Classifier: Programming Language :: Python :: 2.7
Classifier: Programming Language :: Python :: 3
Classifier: Programming Language :: Python :: 3.5
Classifier: Topic :: Utilities
Requires-Dist: requests (>=2.10.0)
Requires-Dist: six (>=1.10.0)
